{
    "ScriptType": "JobConfig",
    "DataLocale": "en-US",
    "OutputErrorPolicy": "Retry",
    "EventsLateArrivalMaxDelayInSeconds": 5,
    "EventsOutOfOrderMaxDelayInSeconds": 5,
    "EventsOutOfOrderPolicy": "Adjust",
    "Sku": {
        "Name": "StandardV2",
        "StreamingUnits": "1"
    },
    "CompatibilityLevel": "1.2",
    "UseSystemAssignedIdentity": false,
    "GlobalStorage": {
        "AccountName": "mainstr",
        "AccountKey": "********",
        "AuthenticationMode": "ConnectionString"
    },
    "ContentStoragePolicy": "SystemAccount",
    "CustomCodeStorage": {
        "AccountName": "mainstr",
        "AccountKey": "********",
        "ContainerName": "con",
        "Path": ""
    },
    "VirtualNetworkConfiguration": {
        "VirtualNetworkName": null,
        "SubnetResourceId": null
    },
    "DataSourceCredentialDomain": "50af46b2-1cfb-4ad0-a0c8-136d1cabca9d.StreamAnalystics",
    "Tags": {}
}